VisualTextAnalyzer/__init__.py
VisualTextAnalyzer/_comm_api.py
VisualTextAnalyzer/_data_preprocessing.py
VisualTextAnalyzer/_demodata.py
VisualTextAnalyzer/build/textExplorer.js
visual_text_explorer-0.1.9.dist-info/LICENSE
visual_text_explorer-0.1.9.dist-info/METADATA
visual_text_explorer-0.1.9.dist-info/WHEEL
visual_text_explorer-0.1.9.dist-info/top_level.txt
visual_text_explorer-0.1.9.dist-info/RECORD
