Metadata-Version: 2.1
Name: visual-text-explorer
Version: 0.1.9
Summary: Visual Text Explorer tool. Enables the exploration and text analysis through word frequency and named entity recognition in Jupyter Notebooks
Home-page: https://github.com/soniacq/TextExplorer
Author: Sonia Castelo
Author-email: s.castelo@nyu.edu
License: UNKNOWN
Platform: UNKNOWN
Classifier: Programming Language :: Python :: 3
Classifier: License :: OSI Approved :: BSD License
Classifier: Operating System :: OS Independent
Requires-Python: >=3.6
Requires-Dist: python-dateutil
Requires-Dist: numpy
Requires-Dist: scipy
Requires-Dist: scikit-learn
Requires-Dist: notebook
Requires-Dist: pandas
Requires-Dist: nltk
Requires-Dist: spacy
